alphazero/__init__.py
alphazero/_version.py
alphazero/connect4/__init__.py
alphazero/connect4/game.py
alphazero/game/__init__.py
alphazero/game/game.py
alphazero/mcts/__init__.py
alphazero/mcts/node.py
alphazero/mcts/play.py
alphazero/mcts/search.py
alphazero/net/__init__.py
alphazero/net/evaluating.py
alphazero/net/learning.py
alphazero/net/net.py
alphazero/tests/__init__.py
alphazero/tests/test_connect4.py
alphazero/utils/__init__.py
alphazero/utils/utils.py
alphazero-0.0.0.dist-info/LICENSE
alphazero-0.0.0.dist-info/METADATA
alphazero-0.0.0.dist-info/WHEEL
alphazero-0.0.0.dist-info/top_level.txt
alphazero-0.0.0.dist-info/RECORD
